LICENSE
MANIFEST.in
README.md
setup.py
ievv_opensource/__init__.py
ievv_opensource/version.json
ievv_opensource.egg-info/PKG-INFO
ievv_opensource.egg-info/SOURCES.txt
ievv_opensource.egg-info/dependency_links.txt
ievv_opensource.egg-info/entry_points.txt
ievv_opensource.egg-info/not-zip-safe
ievv_opensource.egg-info/requires.txt
ievv_opensource.egg-info/top_level.txt
ievv_opensource/ievv_batchframework/__init__.py
ievv_opensource/ievv_batchframework/admin.py
ievv_opensource/ievv_batchframework/batchregistry.py
ievv_opensource/ievv_batchframework/models.py
ievv_opensource/ievv_batchframework/rq_tasks.py
ievv_opensource/ievv_batchframework/test_models.py
ievv_opensource/ievv_batchframework/migrations/0001_initial.py
ievv_opensource/ievv_batchframework/migrations/0002_auto_20160413_0154.py
ievv_opensource/ievv_batchframework/migrations/__init__.py
ievv_opensource/ievv_customsql/__init__.py
ievv_opensource/ievv_customsql/customsql_registry.py
ievv_opensource/ievv_customsql/management/__init__.py
ievv_opensource/ievv_customsql/management/commands/__init__.py
ievv_opensource/ievv_customsql/management/commands/ievvtasks_customsql.py
ievv_opensource/ievv_customsql/tests/__init__.py
ievv_opensource/ievv_customsql/tests/test_customsql_registry.py
ievv_opensource/ievv_db/__init__.py
ievv_opensource/ievv_db/postgres/__init__.py
ievv_opensource/ievv_db/postgres/collate_utils.py
ievv_opensource/ievv_developemail/__init__.py
ievv_opensource/ievv_developemail/admin.py
ievv_opensource/ievv_developemail/email_backend.py
ievv_opensource/ievv_developemail/models.py
ievv_opensource/ievv_developemail/management/__init__.py
ievv_opensource/ievv_developemail/management/commands/__init__.py
ievv_opensource/ievv_developemail/management/commands/ievv_developemail_send_testmail.py
ievv_opensource/ievv_developemail/migrations/0001_initial.py
ievv_opensource/ievv_developemail/migrations/__init__.py
ievv_opensource/ievv_developemail/templates/ievv_developemail/admin/as-html.django.html
ievv_opensource/ievv_developemail/templates/ievv_developemail/admin/as-plain.django.html
ievv_opensource/ievv_developemail/templates/ievv_developemail/admin/as-raw.django.html
ievv_opensource/ievv_developemail/templates/ievv_developemail/admin/base.django.html
