Metadata-Version: 2.1
Name: ievv-opensource
Version: 8.2.6
Summary: The opensource modules from the commercial IEVV Django framework.
Author: Espen Angell Kristiansen, Tor Johansen, Magne Westlie
Author-email: post@appresso.no
License: BSD
Classifier: Development Status :: 4 - Beta
Classifier: Environment :: Web Environment
Classifier: Framework :: Django
Classifier: Intended Audience :: Developers
Classifier: License :: OSI Approved
Classifier: Operating System :: OS Independent
Classifier: Programming Language :: Python
License-File: LICENSE
